[{"link": "https://blog.boot.dev/tutorials/python-tutorial/"}, {"link": "https://brainstation.io/learn/python"}, {"link": "https://codersdaily.in/courses/python-tutorial"}, {"link": "https://cs231n.github.io/python-numpy-tutorial/"}, {"link": "https://docs.python.org/3/library/turtle.html"}, {"link": "https://dotnettutorials.net/course/python-tutorials/"}, {"link": "https://github.com/Akuli/python-tutorial"}, {"link": "https://mindmajix.com/python-tutorial"}, {"link": "https://prepinsta.com/python/"}, {"link": "https://protobuf.dev/getting-started/pythontutorial/"}, {"link": "https://python-course.eu/python-tutorial/"}, {"link": "https://pythonbasics.org/"}, {"link": "https://pythonprogramming.net/beginner-python-programming-tutorials/"}, {"link": "https://pythonspot.com/"}, {"link": "https://stackabuse.com/python-tutorial-for-absolute-beginners/"}, {"link": "https://studyopedia.com/tutorials/python3/"}, {"link": "https://techbeamers.com/python-tutorial-step-by-step/"}, {"link": "https://www.afterhoursprogramming.com/tutorial/python/python-overview/"}, {"link": "https://www.analyticsvidhya.com/blog/2016/01/complete-tutorial-learn-data-science-python-scratch-2/"}, {"link": "https://www.codecademy.com/catalog/language/python"}, {"link": "https://www.codesdope.com/course/python-introduction/"}, {"link": "https://www.digitalocean.com/community/tutorials/python-tutorial-beginners"}, {"link": "https://www.geeksforgeeks.org/python-programming-language/learn-python-tutorial/"}, {"link": "https://www.guru99.com/python-tutorials.html"}, {"link": "https://www.i2tutorials.com/python-tutorial/"}, {"link": "https://www.javatpoint.com/python-tutorial"}, {"link": "https://www.programiz.com/python-programming"}, {"link": "https://www.pythonforbeginners.com/python-tutorial"}, {"link": "https://www.studytonight.com/python/"}, {"link": "https://www.tutlane.com/tutorial/python"}, {"link": "https://www.tutorialkart.com/python/"}, {"link": "https://www.tutorialsfreak.com/python-tutorial"}, {"link": "https://www.tutorialspoint.com/python/index.htm#applications"}, {"link": "https://www.w3schools.com/python/python_intro.asp"}]